{"getting-started_index.md":"DAs4X2Un","getting-started_installation.md":"GpF8hUkR","getting-started_quick-start.md":"D4CwJkp0","guide_fields.md":"Bhdh8PBQ","guide_filters.md":"BDfExvXl","guide_index.md":"1BmeQwkP","guide_pagination.md":"DkaUdSX5","guide_query.md":"BYIv1Atj","guide_relations.md":"BKa3rtf0","guide_schema.md":"DyGd0s7_","guide_sort.md":"CA3wYmtX","index.md":"CG0zMWp4","integrations_expression.md":"P0dVv2tU","integrations_index.md":"C6YPcAlM","integrations_simple.md":"DnroOkaJ","integrations_sql.md":"CB1-52Ny","integrations_typeorm.md":"C5jlF0iT","integrations_url.md":"DjYO4tTj"}
